setup.cfg
setup.py
django_classification_banner/__init__.py
django_classification_banner/context_processors.py
django_classification_banner/models.py
django_classification_banner.egg-info/PKG-INFO
django_classification_banner.egg-info/SOURCES.txt
django_classification_banner.egg-info/dependency_links.txt
django_classification_banner.egg-info/not-zip-safe
django_classification_banner.egg-info/top_level.txt
django_classification_banner/static/django_classification_banner/classification.css
django_classification_banner/templates/django_classification_banner/classification.html
django_classification_banner/templatetags/__init__.py
django_classification_banner/templatetags/classification_banner.py